{"detailed": {"similar": ["extremely detailed", "hyper detailed", "highly detailed", "ultradetailed", "ultra detailed"], "unsimilar": ["baarle ilya kuvshinov", "ilya kuvshinov rossdraws", "artgerm greg rutkowski", "by ilya kuvshinov", "art by artgerm"]}, "highly detailed": {"similar": ["detailed", "extremely detailed", "hyper detailed", "elegant highly", "ultra detailed"], "unsimilar": ["baarle ilya kuvshinov", "ilya kuvshinov rossdraws", "artgerm greg rutkowski", "by ilya kuvshinov", "art by artgerm"]}, "hyper detailed": {"similar": ["detailed", "hyper realism", "extremely detailed", "ultra detailed", "hyper realistic"], "unsimilar": ["baarle ilya kuvshinov", "ilya kuvshinov rossdraws", "artgerm greg rutkowski", "by ilya kuvshinov", "art by artgerm"]}, "extremely detailed": {"similar": ["detailed", "highly detailed", "ultra detailed", "ultradetailed", "hyper detailed"], "unsimilar": ["baarle ilya kuvshinov", "ilya kuvshinov rossdraws", "artgerm greg rutkowski", "by ilya kuvshinov", "art by artgerm"]}, "cinematic": {"similar": ["cinematic lighting", "dystopian", "ominous", "apocalyptic", "atmospheric"], "unsimilar": ["baarle ilya kuvshinov", "ilya kuvshinov rossdraws", "artgerm greg rutkowski", "by ilya kuvshinov", "art by artgerm"]}, "realistic": {"similar": ["photo realistic", "hyper realistic", "ultrarealistic", "photorealistic", "hyperrealistic"], "unsimilar": ["baarle ilya kuvshinov", "ilya kuvshinov rossdraws", "artgerm greg rutkowski", "by ilya kuvshinov", "art by artgerm"]}, "concept art": {"similar": ["painting concept", "art style", "illustration art", "art nouveau", "fantasy art"], "unsimilar": ["baarle ilya kuvshinov", "ilya kuvshinov rossdraws", "artgerm greg rutkowski", "by ilya kuvshinov", "ilya kuvshinov"]}, "sharp": {"similar": ["art sharp", "sharp focus", "smooth sharp", "ominous", "dystopian"], "unsimilar": ["baarle ilya kuvshinov", "ilya kuvshinov rossdraws", "artgerm greg rutkowski", "by ilya kuvshinov", "art by artgerm"]}, "greg rutkowski": {"similar": ["greg rutkowski and", "and greg rutkowski", "greg rutkowski by", "by greg rutkowski", "artgerm greg rutkowski"], "unsimilar": ["baarle ilya kuvshinov", "ilya kuvshinov rossdraws", "digital painting artstation", "art by artgerm", "by ilya kuvshinov"]}, "sharp focus": {"similar": ["sharp focus art", "art sharp focus", "matte sharp focus", "smooth sharp focus", "sharp focus illustration"], "unsimilar": ["baarle ilya kuvshinov", "ilya kuvshinov rossdraws", "artgerm greg rutkowski", "art by artgerm", "by ilya kuvshinov"]}, "high": {"similar": ["high definition", "high resolution", "high quality", "high detail", "high contrast"], "unsimilar": ["baarle ilya kuvshinov", "ilya kuvshinov rossdraws", "artgerm greg rutkowski", "by ilya kuvshinov", "art by artgerm"]}, "trending on artstation": {"similar": ["on artstation concept", "art trending on", "trending on art", "on art station", "painting artstation"], "unsimilar": ["baarle ilya kuvshinov", "ilya kuvshinov rossdraws", "tom bagshaw", "by ilya kuvshinov", "ilya kuvshinov"]}, "cinematic lighting": {"similar": ["cinematic", "dramatic lighting", "dynamic lighting", "studio lighting", "dystopian"], "unsimilar": ["baarle ilya kuvshinov", "ilya kuvshinov rossdraws", "artgerm greg rutkowski", "by ilya kuvshinov", "art by artgerm"]}, "sharp focus illustration": {"similar": ["focus illustration", "sharp focus", "sharp focus art", "art sharp focus", "focus illustration art"], "unsimilar": ["baarle ilya kuvshinov", "artgerm greg rutkowski", "ilya kuvshinov rossdraws", "by ilya kuvshinov", "lois van baarle"]}, "smooth sharp": {"similar": ["art smooth sharp", "smooth sharp focus", "sharp", "art smooth", "art sharp"], "unsimilar": ["baarle ilya kuvshinov", "ilya kuvshinov rossdraws", "artgerm greg rutkowski", "by ilya kuvshinov", "art by artgerm"]}, "smooth sharp focus": {"similar": ["smooth sharp", "sharp focus", "art smooth sharp", "matte sharp focus", "art sharp focus"], "unsimilar": ["baarle ilya kuvshinov", "artgerm greg rutkowski", "ilya kuvshinov rossdraws", "art by artgerm", "by ilya kuvshinov"]}, "octane render": {"similar": ["octane render unreal", "octane render trending", "render unreal", "artstation octane render", "render unreal engine"], "unsimilar": ["baarle ilya kuvshinov", "ilya kuvshinov rossdraws", "artgerm greg rutkowski", "art by artgerm", "by ilya kuvshinov"]}, "digital painting": {"similar": ["digital painting trending", "digital painting concept", "digital art", "digital illustration", "digital painting artstation"], "unsimilar": ["baarle ilya kuvshinov", "ilya kuvshinov rossdraws", "artgerm greg rutkowski", "by ilya kuvshinov", "ilya kuvshinov"]}, "art smooth sharp": {"similar": ["smooth sharp", "art smooth", "art sharp", "smooth sharp focus", "art matte sharp"], "unsimilar": ["baarle ilya kuvshinov", "ilya kuvshinov rossdraws", "artgerm greg rutkowski", "by ilya kuvshinov", "and magali villeneuve"]}, "hyper realistic": {"similar": ["realistic", "hyperrealistic", "hyper realism", "ultra realistic", "hyper detailed"], "unsimilar": ["baarle ilya kuvshinov", "ilya kuvshinov rossdraws", "artgerm greg rutkowski", "by ilya kuvshinov", "art by artgerm"]}, "black": {"similar": ["white", "ominous", "red", "dystopian", "green"], "unsimilar": ["baarle ilya kuvshinov", "ilya kuvshinov rossdraws", "artgerm greg rutkowski", "by ilya kuvshinov", "art by artgerm"]}, "art sharp": {"similar": ["sharp", "art matte sharp", "art sharp focus", "sharp focus art", "art smooth sharp"], "unsimilar": ["baarle ilya kuvshinov", "ilya kuvshinov rossdraws", "artgerm greg rutkowski", "by ilya kuvshinov", "ilya kuvshinov"]}, "art sharp focus": {"similar": ["art sharp focus", "sharp focus", "art sharp", "focus art by", "sharp focus illustration"], "unsimilar": ["baarle ilya kuvshinov", "ilya kuvshinov rossdraws", "artgerm greg rutkowski", "by ilya kuvshinov", "lois van baarle"]}, "high detail": {"similar": ["high", "high definition", "high contrast", "high quality", "intricate detail"], "unsimilar": ["baarle ilya kuvshinov", "ilya kuvshinov rossdraws", "artgerm greg rutkowski", "by ilya kuvshinov", "ilya kuvshinov"]}, "white": {"similar": ["black", "ominous", "red", "dystopian", "green"], "unsimilar": ["baarle ilya kuvshinov", "ilya kuvshinov rossdraws", "artgerm greg rutkowski", "by ilya kuvshinov", "art by artgerm"]}, "high quality": {"similar": ["high", "high resolution", "high definition", "high detail", "high contrast"], "unsimilar": ["baarle ilya kuvshinov", "ilya kuvshinov rossdraws", "artgerm greg rutkowski", "by ilya kuvshinov", "art by artgerm"]}, "photo realistic": {"similar": ["realistic", "photorealistic", "ultra realistic", "ultrarealistic", "hyper realistic"], "unsimilar": ["baarle ilya kuvshinov", "ilya kuvshinov rossdraws", "artgerm greg rutkowski", "by ilya kuvshinov", "lois van baarle"]}, "matte sharp focus": {"similar": ["sharp focus", "sharp focus art", "art sharp focus", "smooth sharp focus", "art matte sharp"], "unsimilar": ["baarle ilya kuvshinov", "ilya kuvshinov rossdraws", "artgerm greg rutkowski", "by ilya kuvshinov", "art by artgerm"]}, "art matte sharp": {"similar": ["art matte", "art sharp", "art smooth sharp", "matte sharp focus", "sharp focus art"], "unsimilar": ["baarle ilya kuvshinov", "ilya kuvshinov rossdraws", "by ilya kuvshinov", "artgerm greg rutkowski", "lois van baarle"]}, "sharp focus art": {"similar": ["art sharp focus", "sharp focus", "art sharp", "focus art by", "sharp focus illustration"], "unsimilar": ["baarle ilya kuvshinov", "ilya kuvshinov rossdraws", "artgerm greg rutkowski", "by ilya kuvshinov", "lois van baarle"]}, "high resolution": {"similar": ["high", "high definition", "high quality", "high contrast", "high detail"], "unsimilar": ["baarle ilya kuvshinov", "ilya kuvshinov rossdraws", "artgerm greg rutkowski", "by ilya kuvshinov", "art by artgerm"]}, "unreal engine": {"similar": ["unreal engine octane", "render unreal engine", "render unreal", "octane render unreal", "ominous"], "unsimilar": ["baarle ilya kuvshinov", "ilya kuvshinov rossdraws", "artgerm greg rutkowski", "art by artgerm", "by ilya kuvshinov"]}, "high contrast": {"similar": ["high", "high detail", "high definition", "high quality", "high resolution"], "unsimilar": ["baarle ilya kuvshinov", "ilya kuvshinov rossdraws", "artgerm greg rutkowski", "by ilya kuvshinov", "art by artgerm"]}, "full": {"similar": ["full body", "ominous", "dystopian", "new", "apocalyptic"], "unsimilar": ["baarle ilya kuvshinov", "ilya kuvshinov rossdraws", "artgerm greg rutkowski", "by ilya kuvshinov", "art by artgerm"]}, "digital art": {"similar": ["digital art by", "digital art trending", "digital painting", "digital illustration", "art nouveau"], "unsimilar": ["baarle ilya kuvshinov", "ilya kuvshinov rossdraws", "artgerm greg rutkowski", "by ilya kuvshinov", "ilya kuvshinov"]}, "high definition": {"similar": ["high", "high resolution", "high detail", "high quality", "high contrast"], "unsimilar": ["baarle ilya kuvshinov", "ilya kuvshinov rossdraws", "artgerm greg rutkowski", "by ilya kuvshinov", "lois van baarle"]}, "ultra": {"similar": ["ultra realistic", "ultra detailed", "dystopian", "ominous", "futuristic"], "unsimilar": ["baarle ilya kuvshinov", "ilya kuvshinov rossdraws", "artgerm greg rutkowski", "art by artgerm", "by ilya kuvshinov"]}, "alphonse mucha": {"similar": ["and alphonse mucha", "alphonse mucha and", "by alphonse mucha", "rutkowski and alphonse", "dystopian"], "unsimilar": ["baarle ilya kuvshinov", "artgerm greg rutkowski", "ilya kuvshinov rossdraws", "art by artgerm", "artgerm and greg"]}, "dramatic": {"similar": ["dramatic lighting", "ominous", "dystopian", "expressive", "apocalyptic"], "unsimilar": ["baarle ilya kuvshinov", "ilya kuvshinov rossdraws", "artgerm greg rutkowski", "art by artgerm", "by ilya kuvshinov"]}, "photorealistic": {"similar": ["realistic", "photo realistic", "ultrarealistic", "ultra realistic", "hyperrealistic"], "unsimilar": ["baarle ilya kuvshinov", "ilya kuvshinov rossdraws", "artgerm greg rutkowski", "by ilya kuvshinov", "by gaston bussiere"]}, "artstation concept": {"similar": ["on artstation concept", "painting artstation concept", "painting artstation", "concept art", "art station"], "unsimilar": ["baarle ilya kuvshinov", "ilya kuvshinov rossdraws", "by ilya kuvshinov", "ilya kuvshinov", "by makoto shinkai"]}, "full body": {"similar": ["full body shot", "full body portrait", "full", "body portrait", "body portrait of"], "unsimilar": ["baarle ilya kuvshinov", "ilya kuvshinov rossdraws", "artgerm greg rutkowski", "by ilya kuvshinov", "digital painting artstation"]}, "focus illustration": {"similar": ["focus illustration art", "sharp focus illustration", "illustration art", "sharp focus", "digital illustration"], "unsimilar": ["baarle ilya kuvshinov", "ilya kuvshinov rossdraws", "artgerm greg rutkowski", "by ilya kuvshinov", "lois van baarle"]}, "red": {"similar": ["black", "ominous", "white", "green", "new"], "unsimilar": ["baarle ilya kuvshinov", "ilya kuvshinov rossdraws", "artgerm greg rutkowski", "by ilya kuvshinov", "digital painting artstation"]}, "and greg rutkowski": {"similar": ["and greg rutkowski", "greg rutkowski", "by greg rutkowski", "greg rutkowski by", "rutkowski and alphonse"], "unsimilar": ["baarle ilya kuvshinov", "ilya kuvshinov rossdraws", "digital painting artstation", "painting artstation concept", "by ilya kuvshinov"]}, "painting artstation": {"similar": ["painting artstation concept", "digital painting artstation", "artstation concept", "art station", "trending on artstation"], "unsimilar": ["baarle ilya kuvshinov", "ilya kuvshinov rossdraws", "by ilya kuvshinov", "ilya kuvshinov", "by makoto shinkai"]}, "digital painting artstation": {"similar": ["painting artstation", "painting artstation concept", "digital painting", "digital painting trending", "digital painting concept"], "unsimilar": ["baarle ilya kuvshinov", "ilya kuvshinov rossdraws", "by ilya kuvshinov", "ilya kuvshinov", "donato giancola"]}, "greg rutkowski and": {"similar": ["greg rutkowski and", "greg rutkowski", "by greg rutkowski", "greg rutkowski by", "rutkowski and alphonse"], "unsimilar": ["baarle ilya kuvshinov", "ilya kuvshinov rossdraws", "digital painting artstation", "painting artstation concept", "by ilya kuvshinov"]}, "black and white": {"similar": ["white", "black", "red", "and intricate environment", "ruan jia and"], "unsimilar": ["baarle ilya kuvshinov", "ilya kuvshinov rossdraws", "artgerm greg rutkowski", "ilya kuvshinov", "anthropomorphic"]}, "ultra realistic": {"similar": ["ultra", "ultrarealistic", "realistic", "ultra detailed", "hyper realistic"], "unsimilar": ["baarle ilya kuvshinov", "ilya kuvshinov rossdraws", "artgerm greg rutkowski", "by ilya kuvshinov", "art by artgerm"]}, "by greg rutkowski": {"similar": ["greg rutkowski by", "greg rutkowski", "greg rutkowski and", "and greg rutkowski", "art by greg"], "unsimilar": ["baarle ilya kuvshinov", "ilya kuvshinov rossdraws", "digital painting artstation", "painting artstation concept", "stanley artgerm lau"]}, "dramatic lighting": {"similar": ["dramatic", "cinematic lighting", "dynamic lighting", "studio lighting", "ominous"], "unsimilar": ["baarle ilya kuvshinov", "ilya kuvshinov rossdraws", "artgerm greg rutkowski", "art by artgerm", "by ilya kuvshinov"]}, "ultra detailed": {"similar": ["ultra", "ultradetailed", "detailed", "extremely detailed", "ultra realistic"], "unsimilar": ["baarle ilya kuvshinov", "ilya kuvshinov rossdraws", "artgerm greg rutkowski", "by ilya kuvshinov", "art by artgerm"]}, "painting artstation concept": {"similar": ["artstation concept", "painting artstation", "on artstation concept", "digital painting artstation", "painting concept"], "unsimilar": ["baarle ilya kuvshinov", "ilya kuvshinov rossdraws", "by ilya kuvshinov", "ilya kuvshinov", "intricate elegant highly"]}, "award winning": {"similar": ["ominous", "dystopian", "dramatic", "futuristic", "comic"], "unsimilar": ["baarle ilya kuvshinov", "ilya kuvshinov rossdraws", "artgerm greg rutkowski", "by ilya kuvshinov", "artgerm and greg"]}, "oil painting": {"similar": ["oil painting of", "oil painting by", "matte painting", "portrait painting", "painting trending"], "unsimilar": ["baarle ilya kuvshinov", "ilya kuvshinov rossdraws", "artgerm greg rutkowski", "by ilya kuvshinov", "ilya kuvshinov"]}, "and alphonse mucha": {"similar": ["alphonse mucha and", "alphonse mucha", "by alphonse mucha", "rutkowski and alphonse", "and lois van"], "unsimilar": ["baarle ilya kuvshinov", "artgerm greg rutkowski", "ilya kuvshinov rossdraws", "digital painting artstation", "painting artstation concept"]}, "full body portrait": {"similar": ["body portrait", "full body", "body portrait of", "full body shot", "full"], "unsimilar": ["baarle ilya kuvshinov", "ilya kuvshinov rossdraws", "artgerm greg rutkowski", "by ilya kuvshinov", "ilya kuvshinov"]}, "art by artgerm": {"similar": ["by stanley artgerm", "artgerm and greg", "stanley artgerm", "stanley artgerm lau", "illustration art by"], "unsimilar": ["unreal engine octane", "baarle ilya kuvshinov", "fantasy intricate elegant", "intricate elegant highly", "ilya kuvshinov rossdraws"]}, "full body shot": {"similar": ["full body", "full body portrait", "full", "body portrait", "body portrait of"], "unsimilar": ["baarle ilya kuvshinov", "ilya kuvshinov rossdraws", "artgerm greg rutkowski", "by ilya kuvshinov", "stanley artgerm lau"]}, "art smooth": {"similar": ["art smooth sharp", "smooth sharp", "art sharp", "art style", "art matte"], "unsimilar": ["baarle ilya kuvshinov", "ilya kuvshinov rossdraws", "artgerm greg rutkowski", "by ilya kuvshinov", "ilya kuvshinov"]}, "intricate elegant": {"similar": ["intricate elegant highly", "fantasy intricate elegant", "elegant highly", "fantasy intricate", "intricate detail"], "unsimilar": ["baarle ilya kuvshinov", "ilya kuvshinov rossdraws", "artgerm greg rutkowski", "by ilya kuvshinov", "art by artgerm"]}, "young": {"similar": ["dystopian", "new", "ominous", "old", "small"], "unsimilar": ["baarle ilya kuvshinov", "ilya kuvshinov rossdraws", "artgerm greg rutkowski", "by ilya kuvshinov", "art by artgerm"]}, "soft": {"similar": ["ominous", "dystopian", "hard", "new", "expressive"], "unsimilar": ["baarle ilya kuvshinov", "ilya kuvshinov rossdraws", "artgerm greg rutkowski", "by ilya kuvshinov", "art by artgerm"]}, "futuristic": {"similar": ["dystopian", "ominous", "apocalyptic", "robotic", "cinematic"], "unsimilar": ["baarle ilya kuvshinov", "ilya kuvshinov rossdraws", "artgerm greg rutkowski", "by ilya kuvshinov", "art by artgerm"]}, "illustration art": {"similar": ["illustration art by", "focus illustration art", "art style", "concept art", "art nouveau"], "unsimilar": ["baarle ilya kuvshinov", "ilya kuvshinov rossdraws", "artgerm greg rutkowski", "by ilya kuvshinov", "by makoto shinkai"]}, "artgerm and greg": {"similar": ["artgerm greg rutkowski", "art by artgerm", "stanley artgerm", "by stanley artgerm", "stanley artgerm lau"], "unsimilar": ["ilya kuvshinov rossdraws", "baarle ilya kuvshinov", "fantasy intricate elegant", "intricate elegant highly", "unreal engine octane"]}, "golden": {"similar": ["golden ratio", "golden hour", "ominous", "dystopian", "apocalyptic"], "unsimilar": ["baarle ilya kuvshinov", "ilya kuvshinov rossdraws", "artgerm greg rutkowski", "art by artgerm", "by ilya kuvshinov"]}, "hyperrealistic": {"similar": ["hyper realistic", "realistic", "photo realistic", "ultrarealistic", "ultra realistic"], "unsimilar": ["baarle ilya kuvshinov", "ilya kuvshinov rossdraws", "artgerm greg rutkowski", "by ilya kuvshinov", "art by artgerm"]}, "illustration art by": {"similar": ["illustration art", "focus art by", "digital art by", "focus illustration art", "art by greg"], "unsimilar": ["baarle ilya kuvshinov", "ilya kuvshinov rossdraws", "artgerm greg rutkowski", "donato giancola", "makoto shinkai"]}, "wide": {"similar": ["wide angle", "ominous", "flat", "large", "dystopian"], "unsimilar": ["baarle ilya kuvshinov", "ilya kuvshinov rossdraws", "artgerm greg rutkowski", "by ilya kuvshinov", "art by artgerm"]}, "symmetrical": {"similar": ["asymmetrical", "dystopian", "ominous", "apocalyptic", "futuristic"], "unsimilar": ["baarle ilya kuvshinov", "ilya kuvshinov rossdraws", "artgerm greg rutkowski", "lois van baarle", "art by artgerm"]}, "volumetric lighting": {"similar": ["cinematic lighting", "dramatic lighting", "studio lighting", "dynamic lighting", "dystopian"], "unsimilar": ["baarle ilya kuvshinov", "artgerm greg rutkowski", "ilya kuvshinov rossdraws", "stanley artgerm lau", "artgerm and greg"]}, "elegant highly": {"similar": ["intricate elegant highly", "intricate elegant", "highly detailed", "ominous", "attractive"], "unsimilar": ["baarle ilya kuvshinov", "ilya kuvshinov rossdraws", "artgerm greg rutkowski", "art by artgerm", "by ilya kuvshinov"]}, "old": {"similar": ["ominous", "new", "dystopian", "young", "red"], "unsimilar": ["baarle ilya kuvshinov", "ilya kuvshinov rossdraws", "artgerm greg rutkowski", "by ilya kuvshinov", "art by artgerm"]}, "focus illustration art": {"similar": ["focus illustration", "illustration art", "focus art by", "illustration art by", "sharp focus illustration"], "unsimilar": ["baarle ilya kuvshinov", "ilya kuvshinov rossdraws", "artgerm greg rutkowski", "by ilya kuvshinov", "by makoto shinkai"]}, "rutkowski and alphonse": {"similar": ["alphonse mucha and", "and alphonse mucha", "greg rutkowski and", "and greg rutkowski", "by alphonse mucha"], "unsimilar": ["baarle ilya kuvshinov", "ilya kuvshinov rossdraws", "digital painting artstation", "painting artstation concept", "fantasy intricate elegant"]}, "matte painting": {"similar": ["art matte", "painting trending", "painting concept", "digital painting", "oil painting"], "unsimilar": ["baarle ilya kuvshinov", "ilya kuvshinov rossdraws", "by ilya kuvshinov", "artgerm greg rutkowski", "ilya kuvshinov"]}, "ilya kuvshinov": {"similar": ["by ilya kuvshinov", "ilya kuvshinov rossdraws", "baarle ilya kuvshinov", "low", "dystopian"], "unsimilar": ["digital painting artstation", "painting artstation concept", "digital painting trending", "artgerm greg rutkowski", "fantasy intricate elegant"]}, "makoto shinkai": {"similar": ["makoto shinkai and", "by makoto shinkai", "shinkai and lois", "ominous", "mystical"], "unsimilar": ["baarle ilya kuvshinov", "ilya kuvshinov rossdraws", "digital painting artstation", "artgerm greg rutkowski", "painting artstation concept"]}, "dynamic": {"similar": ["dynamic lighting", "dystopian", "ominous", "expressive", "dramatic"], "unsimilar": ["baarle ilya kuvshinov", "artgerm greg rutkowski", "ilya kuvshinov rossdraws", "art by artgerm", "by ilya kuvshinov"]}, "sci fi": {"similar": ["dystopian", "ominous", "futuristic", "apocalyptic", "full"], "unsimilar": ["baarle ilya kuvshinov", "ilya kuvshinov rossdraws", "artgerm greg rutkowski", "by ilya kuvshinov", "artgerm and greg"]}, "intricate elegant highly": {"similar": ["elegant highly", "intricate elegant", "fantasy intricate elegant", "highly detailed", "intricate details"], "unsimilar": ["baarle ilya kuvshinov", "ilya kuvshinov rossdraws", "artgerm greg rutkowski", "by ilya kuvshinov", "art by artgerm"]}, "green": {"similar": ["red", "white", "ominous", "dystopian", "black"], "unsimilar": ["baarle ilya kuvshinov", "ilya kuvshinov rossdraws", "artgerm greg rutkowski", "by ilya kuvshinov", "ilya kuvshinov"]}, "wide angle": {"similar": ["wide", "flat", "high", "ominous", "low"], "unsimilar": ["baarle ilya kuvshinov", "artgerm greg rutkowski", "ilya kuvshinov rossdraws", "by ilya kuvshinov", "stanley artgerm lau"]}, "big": {"similar": ["ominous", "huge", "dystopian", "large", "massive"], "unsimilar": ["baarle ilya kuvshinov", "ilya kuvshinov rossdraws", "artgerm greg rutkowski", "by ilya kuvshinov", "art by artgerm"]}, "golden ratio": {"similar": ["golden", "golden hour", "ominous", "dystopian", "apocalyptic"], "unsimilar": ["baarle ilya kuvshinov", "artgerm greg rutkowski", "ilya kuvshinov rossdraws", "art by artgerm", "by ilya kuvshinov"]}, "golden hour": {"similar": ["golden", "golden ratio", "ominous", "apocalyptic", "dystopian"], "unsimilar": ["baarle ilya kuvshinov", "ilya kuvshinov rossdraws", "artgerm greg rutkowski", "by ilya kuvshinov", "art by artgerm"]}, "large": {"similar": ["small", "huge", "ominous", "big", "dystopian"], "unsimilar": ["baarle ilya kuvshinov", "ilya kuvshinov rossdraws", "artgerm greg rutkowski", "by ilya kuvshinov", "ilya kuvshinov"]}, "james jean": {"similar": ["by james jean", "dystopian", "ominous", "new", "short"], "unsimilar": ["baarle ilya kuvshinov", "ilya kuvshinov rossdraws", "artgerm greg rutkowski", "by ilya kuvshinov", "art by artgerm"]}, "studio ghibli": {"similar": ["studio lighting", "ominous", "dystopian", "apocalyptic", "cinematic"], "unsimilar": ["baarle ilya kuvshinov", "ilya kuvshinov rossdraws", "artgerm greg rutkowski", "by ilya kuvshinov", "art by artgerm"]}, "dynamic lighting": {"similar": ["dynamic", "dramatic lighting", "cinematic lighting", "studio lighting", "dystopian"], "unsimilar": ["baarle ilya kuvshinov", "artgerm greg rutkowski", "ilya kuvshinov rossdraws", "art by artgerm", "artgerm and greg"]}, "depth of field": {"similar": ["rule of thirds", "film still of", "body portrait of", "oil painting of", "portrait of beautiful"], "unsimilar": ["baarle ilya kuvshinov", "ilya kuvshinov rossdraws", "artgerm greg rutkowski", "by ilya kuvshinov", "ilya kuvshinov"]}, "gothic": {"similar": ["dystopian", "ominous", "apocalyptic", "cinematic", "atmospheric"], "unsimilar": ["baarle ilya kuvshinov", "ilya kuvshinov rossdraws", "artgerm greg rutkowski", "by ilya kuvshinov", "art by artgerm"]}, "small": {"similar": ["large", "little", "white", "ominous", "short"], "unsimilar": ["baarle ilya kuvshinov", "ilya kuvshinov rossdraws", "artgerm greg rutkowski", "by ilya kuvshinov", "art by artgerm"]}, "intricate details": {"similar": ["intricate detail", "intricate elegant", "fantasy intricate", "detailed", "and intricate environment"], "unsimilar": ["baarle ilya kuvshinov", "ilya kuvshinov rossdraws", "artgerm greg rutkowski", "by ilya kuvshinov", "art by artgerm"]}, "fantasy art": {"similar": ["fantasy intricate", "art nouveau", "art style", "art station", "concept art"], "unsimilar": ["baarle ilya kuvshinov", "ilya kuvshinov rossdraws", "by ilya kuvshinov", "artgerm greg rutkowski", "by makoto shinkai"]}, "craig mullins": {"similar": ["dystopian", "ominous", "sharp", "futuristic", "strong"], "unsimilar": ["baarle ilya kuvshinov", "ilya kuvshinov rossdraws", "artgerm greg rutkowski", "art by artgerm", "by ilya kuvshinov"]}, "atmospheric": {"similar": ["dystopian", "ominous", "apocalyptic", "cinematic", "expressive"], "unsimilar": ["baarle ilya kuvshinov", "ilya kuvshinov rossdraws", "artgerm greg rutkowski", "by ilya kuvshinov", "art by artgerm"]}, "low": {"similar": ["high", "dystopian", "ominous", "small", "flat"], "unsimilar": ["baarle ilya kuvshinov", "ilya kuvshinov rossdraws", "artgerm greg rutkowski", "art by artgerm", "digital painting artstation"]}, "professional": {"similar": ["ominous", "dystopian", "apocalyptic", "expressive", "cinematic"], "unsimilar": ["baarle ilya kuvshinov", "ilya kuvshinov rossdraws", "artgerm greg rutkowski", "by ilya kuvshinov", "art by artgerm"]}, "art trending": {"similar": ["art trending on", "trending on art", "digital art trending", "painting trending", "art nouveau"], "unsimilar": ["baarle ilya kuvshinov", "ilya kuvshinov rossdraws", "by ilya kuvshinov", "artgerm greg rutkowski", "ilya kuvshinov"]}, "fantasy intricate": {"similar": ["fantasy intricate elegant", "fantasy art", "intricate elegant", "intricate details", "intricate detail"], "unsimilar": ["baarle ilya kuvshinov", "ilya kuvshinov rossdraws", "artgerm greg rutkowski", "by ilya kuvshinov", "art by artgerm"]}, "peter mohrbacher": {"similar": ["by peter mohrbacher", "old", "dystopian", "new", "hot"], "unsimilar": ["baarle ilya kuvshinov", "ilya kuvshinov rossdraws", "digital painting artstation", "painting artstation concept", "artgerm greg rutkowski"]}, "oil on canvas": {"similar": ["oil painting of", "oil painting", "oil painting by", "art trending on", "trending on art"], "unsimilar": ["baarle ilya kuvshinov", "ilya kuvshinov rossdraws", "artgerm greg rutkowski", "stanley artgerm lau", "makoto shinkai"]}, "global": {"similar": ["global illumination", "dystopian", "ominous", "apocalyptic", "graphic"], "unsimilar": ["baarle ilya kuvshinov", "ilya kuvshinov rossdraws", "artgerm greg rutkowski", "by ilya kuvshinov", "art by artgerm"]}, "film still": {"similar": ["film still of", "movie still", "dystopian", "ominous", "comic"], "unsimilar": ["baarle ilya kuvshinov", "ilya kuvshinov rossdraws", "artgerm greg rutkowski", "by ilya kuvshinov", "lois van baarle"]}, "ruan jia": {"similar": ["ruan jia and", "red", "low", "new", "dystopian"], "unsimilar": ["baarle ilya kuvshinov", "ilya kuvshinov rossdraws", "artgerm greg rutkowski", "digital painting artstation", "painting artstation concept"]}, "global illumination": {"similar": ["global", "global illumination radiant", "dystopian", "apocalyptic", "ominous"], "unsimilar": ["baarle ilya kuvshinov", "ilya kuvshinov rossdraws", "artgerm greg rutkowski", "by ilya kuvshinov", "artgerm and greg"]}, "japanese": {"similar": ["chinese", "dystopian", "asian", "ominous", "apocalyptic"], "unsimilar": ["baarle ilya kuvshinov", "ilya kuvshinov rossdraws", "artgerm greg rutkowski", "by ilya kuvshinov", "art by artgerm"]}, "aesthetic": {"similar": ["dystopian", "ominous", "apocalyptic", "cinematic", "atmospheric"], "unsimilar": ["baarle ilya kuvshinov", "ilya kuvshinov rossdraws", "artgerm greg rutkowski", "by ilya kuvshinov", "art by artgerm"]}, "real": {"similar": ["realistic", "ominous", "dystopian", "new", "detailed"], "unsimilar": ["baarle ilya kuvshinov", "ilya kuvshinov rossdraws", "artgerm greg rutkowski", "by ilya kuvshinov", "art by artgerm"]}, "short": {"similar": ["ominous", "small", "dystopian", "red", "good"], "unsimilar": ["baarle ilya kuvshinov", "ilya kuvshinov rossdraws", "artgerm greg rutkowski", "by ilya kuvshinov", "art by artgerm"]}, "art by greg": {"similar": ["focus art by", "digital art by", "illustration art by", "greg rutkowski by", "by greg rutkowski"], "unsimilar": ["baarle ilya kuvshinov", "ilya kuvshinov rossdraws", "ilya kuvshinov", "anthropomorphic", "makoto shinkai"]}, "tom bagshaw": {"similar": ["dystopian", "white", "low", "sharp", "ominous"], "unsimilar": ["baarle ilya kuvshinov", "ilya kuvshinov rossdraws", "artgerm greg rutkowski", "digital painting artstation", "painting artstation concept"]}, "new": {"similar": ["dystopian", "next", "ominous", "red", "old"], "unsimilar": ["baarle ilya kuvshinov", "ilya kuvshinov rossdraws", "artgerm greg rutkowski", "by ilya kuvshinov", "art by artgerm"]}, "studio lighting": {"similar": ["studio ghibli", "cinematic lighting", "dramatic lighting", "dynamic lighting", "volumetric lighting"], "unsimilar": ["baarle ilya kuvshinov", "ilya kuvshinov rossdraws", "artgerm greg rutkowski", "by ilya kuvshinov", "artgerm and greg"]}, "art trending on": {"similar": ["art trending on", "art trending", "painting trending on", "render trending on", "on art station"], "unsimilar": ["baarle ilya kuvshinov", "ilya kuvshinov rossdraws", "artgerm greg rutkowski", "by ilya kuvshinov", "ilya kuvshinov"]}, "movie still": {"similar": ["film still", "film still of", "dystopian", "ominous", "comic"], "unsimilar": ["baarle ilya kuvshinov", "ilya kuvshinov rossdraws", "artgerm greg rutkowski", "by ilya kuvshinov", "lois van baarle"]}, "comic": {"similar": ["dystopian", "ominous", "apocalyptic", "expressive", "cinematic"], "unsimilar": ["baarle ilya kuvshinov", "ilya kuvshinov rossdraws", "artgerm greg rutkowski", "by ilya kuvshinov", "art by artgerm"]}, "natural": {"similar": ["ominous", "dystopian", "apocalyptic", "incredible", "new"], "unsimilar": ["baarle ilya kuvshinov", "ilya kuvshinov rossdraws", "artgerm greg rutkowski", "by ilya kuvshinov", "art by artgerm"]}, "art nouveau": {"similar": ["art style", "art trending", "art station", "fantasy art", "concept art"], "unsimilar": ["baarle ilya kuvshinov", "ilya kuvshinov rossdraws", "by ilya kuvshinov", "artgerm greg rutkowski", "by makoto shinkai"]}, "magical": {"similar": ["mystical", "dystopian", "ominous", "mysterious", "apocalyptic"], "unsimilar": ["baarle ilya kuvshinov", "ilya kuvshinov rossdraws", "artgerm greg rutkowski", "by ilya kuvshinov", "art by artgerm"]}, "gorgeous": {"similar": ["ominous", "dystopian", "apocalyptic", "incredible", "huge"], "unsimilar": ["baarle ilya kuvshinov", "ilya kuvshinov rossdraws", "artgerm greg rutkowski", "by ilya kuvshinov", "art by artgerm"]}, "render unreal": {"similar": ["octane render unreal", "render unreal engine", "octane render", "unreal engine", "octane render trending"], "unsimilar": ["baarle ilya kuvshinov", "artgerm greg rutkowski", "ilya kuvshinov rossdraws", "art by artgerm", "by ilya kuvshinov"]}, "huge": {"similar": ["massive", "ominous", "dystopian", "large", "big"], "unsimilar": ["baarle ilya kuvshinov", "ilya kuvshinov rossdraws", "artgerm greg rutkowski", "art by artgerm", "by ilya kuvshinov"]}, "render unreal engine": {"similar": ["unreal engine", "render unreal", "unreal engine octane", "octane render unreal", "octane render"], "unsimilar": ["baarle ilya kuvshinov", "ilya kuvshinov rossdraws", "artgerm greg rutkowski", "art by artgerm", "by ilya kuvshinov"]}, "anthropomorphic": {"similar": ["anamorphic", "ominous", "dystopian", "apocalyptic", "atmospheric"], "unsimilar": ["baarle ilya kuvshinov", "ilya kuvshinov rossdraws", "artgerm greg rutkowski", "digital painting artstation", "by ilya kuvshinov"]}, "modern": {"similar": ["dystopian", "ominous", "new", "futuristic", "apocalyptic"], "unsimilar": ["baarle ilya kuvshinov", "ilya kuvshinov rossdraws", "artgerm greg rutkowski", "by ilya kuvshinov", "art by artgerm"]}, "ross tran": {"similar": ["dystopian", "ominous", "expressive", "white", "red"], "unsimilar": ["baarle ilya kuvshinov", "ilya kuvshinov rossdraws", "artgerm greg rutkowski", "by ilya kuvshinov", "art by artgerm"]}, "fantasy intricate elegant": {"similar": ["intricate elegant", "fantasy intricate", "intricate elegant highly", "fantasy art", "elegant highly"], "unsimilar": ["baarle ilya kuvshinov", "ilya kuvshinov rossdraws", "artgerm greg rutkowski", "by ilya kuvshinov", "art by artgerm"]}, "lois van": {"similar": ["and lois van", "dystopian", "apocalyptic", "ominous", "atmospheric"], "unsimilar": ["baarle ilya kuvshinov", "ilya kuvshinov rossdraws", "artgerm greg rutkowski", "by ilya kuvshinov", "digital painting artstation"]}, "ray tracing": {"similar": ["ominous", "dystopian", "artistic", "new", "apocalyptic"], "unsimilar": ["baarle ilya kuvshinov", "ilya kuvshinov rossdraws", "artgerm greg rutkowski", "by ilya kuvshinov", "art by artgerm"]}, "van baarle": {"similar": ["van baarle ilya", "lois van baarle", "and lois van", "lois van", "baarle ilya kuvshinov"], "unsimilar": ["ilya kuvshinov rossdraws", "artgerm greg rutkowski", "fantasy intricate elegant", "intricate elegant highly", "by ilya kuvshinov"]}, "lois van baarle": {"similar": ["van baarle", "van baarle ilya", "and lois van", "lois van", "baarle ilya kuvshinov"], "unsimilar": ["ilya kuvshinov rossdraws", "fantasy intricate elegant", "intricate elegant highly", "digital painting artstation", "digital painting trending"]}, "clear": {"similar": ["ominous", "dystopian", "white", "black", "red"], "unsimilar": ["baarle ilya kuvshinov", "ilya kuvshinov rossdraws", "artgerm greg rutkowski", "by ilya kuvshinov", "art by artgerm"]}, "loish": {"similar": ["dystopian", "low", "ominous", "new", "high"], "unsimilar": ["baarle ilya kuvshinov", "ilya kuvshinov rossdraws", "artgerm greg rutkowski", "digital painting artstation", "by ilya kuvshinov"]}, "krenz cushart": {"similar": ["art style", "on art station", "art station", "art matte", "art nouveau"], "unsimilar": ["baarle ilya kuvshinov", "donato giancola", "fantasy intricate elegant", "charlie bowater", "intricate elegant highly"]}, "hyper realism": {"similar": ["hyper realistic", "hyper detailed", "dystopian", "realistic", "hyperrealistic"], "unsimilar": ["baarle ilya kuvshinov", "ilya kuvshinov rossdraws", "artgerm greg rutkowski", "by ilya kuvshinov", "art by artgerm"]}, "norman rockwell": {"similar": ["dystopian", "ominous", "small", "realistic", "apocalyptic"], "unsimilar": ["baarle ilya kuvshinov", "ilya kuvshinov rossdraws", "artgerm greg rutkowski", "by ilya kuvshinov", "art by artgerm"]}, "portrait painting": {"similar": ["portrait painting of", "character portrait", "painting concept", "body portrait", "painting trending"], "unsimilar": ["baarle ilya kuvshinov", "ilya kuvshinov rossdraws", "artgerm greg rutkowski", "by ilya kuvshinov", "lois van baarle"]}, "portrait of beautiful": {"similar": ["portrait painting of", "body portrait of", "portrait painting", "body portrait", "character portrait"], "unsimilar": ["baarle ilya kuvshinov", "ilya kuvshinov rossdraws", "artgerm greg rutkowski", "by ilya kuvshinov", "ilya kuvshinov"]}, "dan mumford": {"similar": ["dystopian", "ominous", "expressive", "cinematic", "huge"], "unsimilar": ["baarle ilya kuvshinov", "ilya kuvshinov rossdraws", "artgerm greg rutkowski", "by ilya kuvshinov", "art by artgerm"]}, "global illumination radiant": {"similar": ["global illumination", "illumination radiant light", "global", "ominous", "apocalyptic"], "unsimilar": ["baarle ilya kuvshinov", "ilya kuvshinov rossdraws", "artgerm greg rutkowski", "by ilya kuvshinov", "lois van baarle"]}, "vibrant colors": {"similar": ["ominous", "attractive", "gorgeous", "new", "dramatic"], "unsimilar": ["baarle ilya kuvshinov", "ilya kuvshinov rossdraws", "artgerm greg rutkowski", "by ilya kuvshinov", "art by artgerm"]}, "art matte": {"similar": ["art matte sharp", "matte painting", "art style", "art smooth", "art nouveau"], "unsimilar": ["baarle ilya kuvshinov", "ilya kuvshinov rossdraws", "by ilya kuvshinov", "artgerm greg rutkowski", "ilya kuvshinov"]}, "digital illustration": {"similar": ["digital art", "digital painting", "illustration art", "focus illustration", "digital art by"], "unsimilar": ["baarle ilya kuvshinov", "ilya kuvshinov rossdraws", "artgerm greg rutkowski", "by ilya kuvshinov", "lois van baarle"]}, "makoto shinkai and": {"similar": ["makoto shinkai", "by makoto shinkai", "shinkai and lois", "ruan jia and", "and alphonse mucha"], "unsimilar": ["baarle ilya kuvshinov", "fantasy intricate elegant", "ilya kuvshinov rossdraws", "digital painting artstation", "artgerm greg rutkowski"]}, "rich": {"similar": ["ominous", "dystopian", "apocalyptic", "strong", "high"], "unsimilar": ["baarle ilya kuvshinov", "ilya kuvshinov rossdraws", "artgerm greg rutkowski", "by ilya kuvshinov", "art by artgerm"]}, "donato giancola": {"similar": ["ominous", "dystopian", "good", "real", "red"], "unsimilar": ["baarle ilya kuvshinov", "ilya kuvshinov rossdraws", "artgerm greg rutkowski", "digital painting artstation", "art by artgerm"]}, "magali villeneuve": {"similar": ["and magali villeneuve", "ominous", "apocalyptic", "angry", "dystopian"], "unsimilar": ["baarle ilya kuvshinov", "ilya kuvshinov rossdraws", "artgerm greg rutkowski", "art by artgerm", "digital painting artstation"]}, "gaston bussiere": {"similar": ["by gaston bussiere", "dystopian", "high", "art style", "strong"], "unsimilar": ["baarle ilya kuvshinov", "ilya kuvshinov rossdraws", "by ilya kuvshinov", "artgerm greg rutkowski", "ilya kuvshinov"]}, "painting trending": {"similar": ["painting trending on", "digital painting trending", "art trending", "matte painting", "painting concept"], "unsimilar": ["baarle ilya kuvshinov", "ilya kuvshinov rossdraws", "by ilya kuvshinov", "artgerm greg rutkowski", "ilya kuvshinov"]}, "hard": {"similar": ["soft", "dystopian", "ominous", "good", "massive"], "unsimilar": ["baarle ilya kuvshinov", "ilya kuvshinov rossdraws", "by ilya kuvshinov", "artgerm greg rutkowski", "art by artgerm"]}, "body portrait": {"similar": ["body portrait of", "full body portrait", "portrait painting", "full body", "character portrait"], "unsimilar": ["baarle ilya kuvshinov", "ilya kuvshinov rossdraws", "artgerm greg rutkowski", "by ilya kuvshinov", "lois van baarle"]}, "medium shot": {"similar": ["small", "large", "full body shot", "ominous", "short"], "unsimilar": ["baarle ilya kuvshinov", "ilya kuvshinov rossdraws", "artgerm greg rutkowski", "by ilya kuvshinov", "lois van baarle"]}, "intricate detail": {"similar": ["intricate details", "high detail", "intricate elegant", "fantasy intricate", "detailed"], "unsimilar": ["baarle ilya kuvshinov", "ilya kuvshinov rossdraws", "artgerm greg rutkowski", "by ilya kuvshinov", "ilya kuvshinov"]}, "art style": {"similar": ["art nouveau", "art station", "art trending", "concept art", "illustration art"], "unsimilar": ["baarle ilya kuvshinov", "ilya kuvshinov rossdraws", "artgerm greg rutkowski", "by ilya kuvshinov", "by makoto shinkai"]}, "color scheme": {"similar": ["ominous", "new", "white", "dystopian", "red"], "unsimilar": ["baarle ilya kuvshinov", "ilya kuvshinov rossdraws", "artgerm greg rutkowski", "by ilya kuvshinov", "art by artgerm"]}, "facial": {"similar": ["dystopian", "ominous", "apocalyptic", "expressive", "natural"], "unsimilar": ["baarle ilya kuvshinov", "ilya kuvshinov rossdraws", "artgerm greg rutkowski", "by ilya kuvshinov", "art by artgerm"]}, "octane render unreal": {"similar": ["render unreal", "octane render", "render unreal engine", "octane render trending", "unreal engine octane"], "unsimilar": ["baarle ilya kuvshinov", "artgerm greg rutkowski", "ilya kuvshinov rossdraws", "art by artgerm", "artgerm and greg"]}, "character portrait": {"similar": ["character design", "portrait painting", "body portrait", "portrait painting of", "portrait of beautiful"], "unsimilar": ["baarle ilya kuvshinov", "ilya kuvshinov rossdraws", "artgerm greg rutkowski", "by ilya kuvshinov", "lois van baarle"]}, "painting concept": {"similar": ["digital painting concept", "concept art", "portrait painting", "matte painting", "painting artstation concept"], "unsimilar": ["baarle ilya kuvshinov", "ilya kuvshinov rossdraws", "artgerm greg rutkowski", "by ilya kuvshinov", "ilya kuvshinov"]}, "portrait painting of": {"similar": ["portrait painting", "portrait of beautiful", "body portrait of", "oil painting of", "painting concept"], "unsimilar": ["baarle ilya kuvshinov", "ilya kuvshinov rossdraws", "artgerm greg rutkowski", "ilya kuvshinov", "by ilya kuvshinov"]}, "little": {"similar": ["dystopian", "small", "ominous", "tiny", "apocalyptic"], "unsimilar": ["baarle ilya kuvshinov", "ilya kuvshinov rossdraws", "by ilya kuvshinov", "artgerm greg rutkowski", "ilya kuvshinov"]}, "thomas kinkade": {"similar": ["dystopian", "ominous", "old", "white", "high"], "unsimilar": ["baarle ilya kuvshinov", "ilya kuvshinov rossdraws", "artgerm greg rutkowski", "by ilya kuvshinov", "art by artgerm"]}, "digital art trending": {"similar": ["digital art", "art trending", "digital painting trending", "digital art by", "art trending on"], "unsimilar": ["baarle ilya kuvshinov", "ilya kuvshinov rossdraws", "by ilya kuvshinov", "artgerm greg rutkowski", "ilya kuvshinov"]}, "charlie bowater": {"similar": ["small", "red", "white", "dystopian", "green"], "unsimilar": ["baarle ilya kuvshinov", "ilya kuvshinov rossdraws", "artgerm greg rutkowski", "by ilya kuvshinov", "art by artgerm"]}, "character design": {"similar": ["character portrait", "expressive", "ominous", "graphic", "dystopian"], "unsimilar": ["baarle ilya kuvshinov", "artgerm greg rutkowski", "ilya kuvshinov rossdraws", "by ilya kuvshinov", "by makoto shinkai"]}, "painting trending on": {"similar": ["painting trending", "trending on art", "art trending on", "render trending on", "digital painting trending"], "unsimilar": ["baarle ilya kuvshinov", "ilya kuvshinov rossdraws", "artgerm greg rutkowski", "by ilya kuvshinov", "ilya kuvshinov"]}, "artstation cgsociety": {"similar": ["artstation concept", "painting artstation", "art station", "artstation octane render", "on artstation concept"], "unsimilar": ["baarle ilya kuvshinov", "ilya kuvshinov rossdraws", "by ilya kuvshinov", "lois van baarle", "by makoto shinkai"]}, "happy": {"similar": ["expressive", "dystopian", "ominous", "apocalyptic", "good"], "unsimilar": ["baarle ilya kuvshinov", "ilya kuvshinov rossdraws", "artgerm greg rutkowski", "by ilya kuvshinov", "art by artgerm"]}, "oil painting of": {"similar": ["oil painting", "oil painting by", "portrait painting of", "oil on canvas", "painting trending on"], "unsimilar": ["baarle ilya kuvshinov", "ilya kuvshinov rossdraws", "artgerm greg rutkowski", "ilya kuvshinov", "by ilya kuvshinov"]}, "wayne barlowe": {"similar": ["dystopian", "ominous", "low", "good", "high"], "unsimilar": ["baarle ilya kuvshinov", "ilya kuvshinov rossdraws", "by ilya kuvshinov", "artgerm greg rutkowski", "painting artstation concept"]}, "art station": {"similar": ["on art station", "art style", "art nouveau", "art trending", "art sharp"], "unsimilar": ["baarle ilya kuvshinov", "ilya kuvshinov rossdraws", "artgerm greg rutkowski", "by ilya kuvshinov", "ilya kuvshinov"]}, "frank frazetta": {"similar": ["dystopian", "ominous", "apocalyptic", "white", "visible"], "unsimilar": ["baarle ilya kuvshinov", "ilya kuvshinov rossdraws", "by ilya kuvshinov", "digital painting artstation", "painting artstation concept"]}, "alphonse mucha and": {"similar": ["alphonse mucha and", "alphonse mucha", "by alphonse mucha", "rutkowski and alphonse", "and lois van"], "unsimilar": ["baarle ilya kuvshinov", "artgerm greg rutkowski", "ilya kuvshinov rossdraws", "digital painting artstation", "painting artstation concept"]}, "stanley artgerm": {"similar": ["stanley artgerm lau", "by stanley artgerm", "art by artgerm", "artgerm and greg", "artgerm greg rutkowski"], "unsimilar": ["baarle ilya kuvshinov", "ilya kuvshinov rossdraws", "by ilya kuvshinov", "intricate elegant highly", "fantasy intricate elegant"]}, "edward hopper": {"similar": ["dystopian", "ominous", "futuristic", "new", "apocalyptic"], "unsimilar": ["baarle ilya kuvshinov", "artgerm greg rutkowski", "ilya kuvshinov rossdraws", "by ilya kuvshinov", "art by artgerm"]}, "single": {"similar": ["dystopian", "ominous", "expressive", "white", "apocalyptic"], "unsimilar": ["baarle ilya kuvshinov", "ilya kuvshinov rossdraws", "by ilya kuvshinov", "artgerm greg rutkowski", "art by artgerm"]}, "ilya kuvshinov rossdraws": {"similar": ["ilya kuvshinov", "by ilya kuvshinov", "baarle ilya kuvshinov", "on art station", "krenz cushart"], "unsimilar": ["digital painting artstation", "digital painting trending", "fantasy intricate elegant", "intricate elegant highly", "painting artstation concept"]}, "by ilya kuvshinov": {"similar": ["ilya kuvshinov", "ilya kuvshinov rossdraws", "baarle ilya kuvshinov", "focus art by", "illustration art by"], "unsimilar": ["fantasy intricate elegant", "digital painting artstation", "digital painting trending", "intricate elegant highly", "painting artstation concept"]}, "strong": {"similar": ["ominous", "powerful", "good", "dystopian", "heavy"], "unsimilar": ["baarle ilya kuvshinov", "ilya kuvshinov rossdraws", "artgerm greg rutkowski", "art by artgerm", "by ilya kuvshinov"]}, "complex": {"similar": ["dystopian", "ominous", "expressive", "apocalyptic", "massive"], "unsimilar": ["baarle ilya kuvshinov", "ilya kuvshinov rossdraws", "artgerm greg rutkowski", "by ilya kuvshinov", "art by artgerm"]}, "heavy": {"similar": ["ominous", "dystopian", "apocalyptic", "huge", "strong"], "unsimilar": ["baarle ilya kuvshinov", "ilya kuvshinov rossdraws", "artgerm greg rutkowski", "by ilya kuvshinov", "art by artgerm"]}, "rule of thirds": {"similar": ["depth of field", "dystopian", "league of legends", "film still of", "ominous"], "unsimilar": ["baarle ilya kuvshinov", "ilya kuvshinov rossdraws", "artgerm greg rutkowski", "by ilya kuvshinov", "ilya kuvshinov"]}, "by makoto shinkai": {"similar": ["makoto shinkai", "makoto shinkai and", "shinkai and lois", "by alphonse mucha", "art by greg"], "unsimilar": ["baarle ilya kuvshinov", "fantasy intricate elegant", "digital painting artstation", "artgerm greg rutkowski", "ilya kuvshinov rossdraws"]}, "attractive": {"similar": ["ominous", "expressive", "dystopian", "new", "futuristic"], "unsimilar": ["baarle ilya kuvshinov", "ilya kuvshinov rossdraws", "artgerm greg rutkowski", "by ilya kuvshinov", "art by artgerm"]}, "organic": {"similar": ["ominous", "dystopian", "expressive", "apocalyptic", "graphic"], "unsimilar": ["baarle ilya kuvshinov", "ilya kuvshinov rossdraws", "by ilya kuvshinov", "artgerm greg rutkowski", "art by artgerm"]}, "many": {"similar": ["dystopian", "ominous", "huge", "expressive", "apocalyptic"], "unsimilar": ["baarle ilya kuvshinov", "ilya kuvshinov rossdraws", "artgerm greg rutkowski", "by ilya kuvshinov", "art by artgerm"]}, "cybernetic": {"similar": ["dystopian", "white", "ominous", "green", "new"], "unsimilar": ["baarle ilya kuvshinov", "ilya kuvshinov rossdraws", "artgerm greg rutkowski", "by ilya kuvshinov", "painting artstation concept"]}, "mechanical": {"similar": ["dystopian", "ominous", "apocalyptic", "cinematic", "mystical"], "unsimilar": ["baarle ilya kuvshinov", "ilya kuvshinov rossdraws", "artgerm greg rutkowski", "by ilya kuvshinov", "art by artgerm"]}, "tiny": {"similar": ["dystopian", "ominous", "little", "apocalyptic", "small"], "unsimilar": ["baarle ilya kuvshinov", "ilya kuvshinov rossdraws", "artgerm greg rutkowski", "by ilya kuvshinov", "art by artgerm"]}, "next": {"similar": ["new", "dystopian", "ominous", "apocalyptic", "expressive"], "unsimilar": ["baarle ilya kuvshinov", "ilya kuvshinov rossdraws", "artgerm greg rutkowski", "by ilya kuvshinov", "art by artgerm"]}, "visual": {"similar": ["dystopian", "ominous", "cinematic", "apocalyptic", "visible"], "unsimilar": ["baarle ilya kuvshinov", "ilya kuvshinov rossdraws", "artgerm greg rutkowski", "by ilya kuvshinov", "art by artgerm"]}, "scary": {"similar": ["ominous", "dystopian", "apocalyptic", "expressive", "dramatic"], "unsimilar": ["baarle ilya kuvshinov", "ilya kuvshinov rossdraws", "artgerm greg rutkowski", "by ilya kuvshinov", "art by artgerm"]}, "mixed": {"similar": ["dystopian", "ominous", "expressive", "apocalyptic", "new"], "unsimilar": ["baarle ilya kuvshinov", "ilya kuvshinov rossdraws", "artgerm greg rutkowski", "by ilya kuvshinov", "art by artgerm"]}, "digital painting trending": {"similar": ["digital painting", "painting trending", "digital art trending", "painting trending on", "digital painting concept"], "unsimilar": ["baarle ilya kuvshinov", "ilya kuvshinov rossdraws", "artgerm greg rutkowski", "by ilya kuvshinov", "ilya kuvshinov"]}, "van baarle ilya": {"similar": ["van baarle", "lois van baarle", "baarle ilya kuvshinov", "and lois van", "lois van"], "unsimilar": ["fantasy intricate elegant", "intricate elegant highly", "digital painting artstation", "smooth sharp focus", "matte sharp focus"]}, "open": {"similar": ["ominous", "empty", "apocalyptic", "dystopian", "low"], "unsimilar": ["baarle ilya kuvshinov", "ilya kuvshinov rossdraws", "artgerm greg rutkowski", "art by artgerm", "by ilya kuvshinov"]}, "baarle ilya kuvshinov": {"similar": ["ilya kuvshinov", "by ilya kuvshinov", "ilya kuvshinov rossdraws", "van baarle ilya", "van baarle"], "unsimilar": ["fantasy intricate elegant", "intricate elegant highly", "digital painting trending", "hyperrealistic", "global illumination radiant"]}, "artistic": {"similar": ["ominous", "dystopian", "apocalyptic", "expressive", "dramatic"], "unsimilar": ["baarle ilya kuvshinov", "ilya kuvshinov rossdraws", "by ilya kuvshinov", "artgerm greg rutkowski", "ilya kuvshinov"]}, "dystopian": {"similar": ["ominous", "apocalyptic", "futuristic", "expressive", "cinematic"], "unsimilar": ["baarle ilya kuvshinov", "ilya kuvshinov rossdraws", "artgerm greg rutkowski", "by ilya kuvshinov", "art by artgerm"]}, "and intricate environment": {"similar": ["intricate detail", "intricate elegant", "intricate details", "fantasy intricate", "small"], "unsimilar": ["baarle ilya kuvshinov", "ilya kuvshinov rossdraws", "artgerm greg rutkowski", "by ilya kuvshinov", "ilya kuvshinov"]}, "by james jean": {"similar": ["james jean", "oil painting by", "art by greg", "illustration art by", "focus art by"], "unsimilar": ["baarle ilya kuvshinov", "ilya kuvshinov rossdraws", "artgerm greg rutkowski", "digital painting artstation", "ilya kuvshinov"]}, "digital painting concept": {"similar": ["digital painting", "painting concept", "digital painting trending", "digital art", "digital painting artstation"], "unsimilar": ["baarle ilya kuvshinov", "ilya kuvshinov rossdraws", "artgerm greg rutkowski", "by ilya kuvshinov", "ilya kuvshinov"]}, "and lois van": {"similar": ["lois van", "shinkai and lois", "lois van baarle", "and intricate environment", "alphonse mucha and"], "unsimilar": ["baarle ilya kuvshinov", "ilya kuvshinov rossdraws", "artgerm greg rutkowski", "digital painting artstation", "by ilya kuvshinov"]}, "flat": {"similar": ["dystopian", "ominous", "low", "wide", "apocalyptic"], "unsimilar": ["baarle ilya kuvshinov", "ilya kuvshinov rossdraws", "artgerm greg rutkowski", "by ilya kuvshinov", "art by artgerm"]}, "chinese": {"similar": ["japanese", "dystopian", "asian", "ominous", "victorian"], "unsimilar": ["baarle ilya kuvshinov", "artgerm greg rutkowski", "ilya kuvshinov rossdraws", "by ilya kuvshinov", "art by artgerm"]}, "massive": {"similar": ["huge", "dystopian", "ominous", "apocalyptic", "cinematic"], "unsimilar": ["baarle ilya kuvshinov", "ilya kuvshinov rossdraws", "artgerm greg rutkowski", "by ilya kuvshinov", "art by artgerm"]}, "oil painting by": {"similar": ["oil painting", "oil painting of", "oil on canvas", "portrait painting of", "digital art by"], "unsimilar": ["baarle ilya kuvshinov", "ilya kuvshinov rossdraws", "artgerm greg rutkowski", "ilya kuvshinov", "donato giancola"]}, "american": {"similar": ["dystopian", "ominous", "apocalyptic", "asian", "victorian"], "unsimilar": ["baarle ilya kuvshinov", "ilya kuvshinov rossdraws", "artgerm greg rutkowski", "by ilya kuvshinov", "art by artgerm"]}, "close up portrait": {"similar": ["portrait painting", "portrait painting of", "portrait of beautiful", "body portrait", "character portrait"], "unsimilar": ["baarle ilya kuvshinov", "artgerm greg rutkowski", "ilya kuvshinov rossdraws", "by ilya kuvshinov", "by makoto shinkai"]}, "victorian": {"similar": ["dystopian", "ominous", "futuristic", "apocalyptic", "mystical"], "unsimilar": ["baarle ilya kuvshinov", "ilya kuvshinov rossdraws", "artgerm greg rutkowski", "by ilya kuvshinov", "art by artgerm"]}, "film still of": {"similar": ["film still", "movie still", "depth of field", "oil painting of", "rule of thirds"], "unsimilar": ["baarle ilya kuvshinov", "ilya kuvshinov rossdraws", "artgerm greg rutkowski", "by ilya kuvshinov", "ilya kuvshinov"]}, "graphic": {"similar": ["dystopian", "ominous", "visual", "apocalyptic", "expressive"], "unsimilar": ["baarle ilya kuvshinov", "ilya kuvshinov rossdraws", "artgerm greg rutkowski", "by ilya kuvshinov", "by makoto shinkai"]}, "ominous": {"similar": ["dystopian", "apocalyptic", "dramatic", "atmospheric", "cinematic"], "unsimilar": ["baarle ilya kuvshinov", "ilya kuvshinov rossdraws", "artgerm greg rutkowski", "by ilya kuvshinov", "art by artgerm"]}, "mystical": {"similar": ["dystopian", "ominous", "mysterious", "magical", "apocalyptic"], "unsimilar": ["baarle ilya kuvshinov", "ilya kuvshinov rossdraws", "artgerm greg rutkowski", "by ilya kuvshinov", "art by artgerm"]}, "render trending on": {"similar": ["octane render trending", "trending on art", "art trending on", "painting trending on", "art trending"], "unsimilar": ["baarle ilya kuvshinov", "ilya kuvshinov rossdraws", "artgerm greg rutkowski", "by ilya kuvshinov", "lois van baarle"]}, "greg rutkowski by": {"similar": ["greg rutkowski by", "greg rutkowski", "and greg rutkowski", "greg rutkowski and", "art by greg"], "unsimilar": ["baarle ilya kuvshinov", "ilya kuvshinov rossdraws", "digital painting artstation", "painting artstation concept", "stanley artgerm lau"]}, "stanley artgerm lau": {"similar": ["stanley artgerm", "by stanley artgerm", "art by artgerm", "artgerm and greg", "artgerm greg rutkowski"], "unsimilar": ["baarle ilya kuvshinov", "ilya kuvshinov rossdraws", "fantasy intricate elegant", "by ilya kuvshinov", "intricate elegant highly"]}, "dead": {"similar": ["ominous", "dystopian", "apocalyptic", "old", "angry"], "unsimilar": ["baarle ilya kuvshinov", "ilya kuvshinov rossdraws", "artgerm greg rutkowski", "by ilya kuvshinov", "art by artgerm"]}, "angry": {"similar": ["ominous", "dystopian", "expressive", "cinematic", "scary"], "unsimilar": ["baarle ilya kuvshinov", "ilya kuvshinov rossdraws", "artgerm greg rutkowski", "by ilya kuvshinov", "art by artgerm"]}, "by alphonse mucha": {"similar": ["alphonse mucha", "alphonse mucha and", "and alphonse mucha", "rutkowski and alphonse", "focus art by"], "unsimilar": ["baarle ilya kuvshinov", "artgerm greg rutkowski", "ilya kuvshinov rossdraws", "digital painting artstation", "painting artstation concept"]}, "shinkai and lois": {"similar": ["makoto shinkai and", "and lois van", "makoto shinkai", "by makoto shinkai", "lois van"], "unsimilar": ["baarle ilya kuvshinov", "ilya kuvshinov rossdraws", "artgerm greg rutkowski", "digital painting artstation", "fantasy intricate elegant"]}, "by peter mohrbacher": {"similar": ["peter mohrbacher", "art by greg", "by james jean", "digital art by", "illustration art by"], "unsimilar": ["baarle ilya kuvshinov", "fantasy intricate elegant", "digital painting artstation", "ilya kuvshinov rossdraws", "donato giancola"]}, "mysterious": {"similar": ["ominous", "dystopian", "mystical", "apocalyptic", "cinematic"], "unsimilar": ["baarle ilya kuvshinov", "ilya kuvshinov rossdraws", "artgerm greg rutkowski", "art by artgerm", "by ilya kuvshinov"]}, "illumination radiant light": {"similar": ["global illumination radiant", "global illumination", "ominous", "cinematic lighting", "dramatic lighting"], "unsimilar": ["baarle ilya kuvshinov", "ilya kuvshinov rossdraws", "artgerm greg rutkowski", "by ilya kuvshinov", "art by artgerm"]}, "artstation octane render": {"similar": ["octane render", "painting artstation", "artstation concept", "octane render trending", "octane render unreal"], "unsimilar": ["baarle ilya kuvshinov", "ilya kuvshinov rossdraws", "by ilya kuvshinov", "lois van baarle", "by peter mohrbacher"]}, "octane render trending": {"similar": ["octane render", "render trending on", "octane render unreal", "render unreal", "art trending"], "unsimilar": ["baarle ilya kuvshinov", "ilya kuvshinov rossdraws", "artgerm greg rutkowski", "by ilya kuvshinov", "art by artgerm"]}, "empty": {"similar": ["dystopian", "ominous", "apocalyptic", "open", "expressive"], "unsimilar": ["baarle ilya kuvshinov", "ilya kuvshinov rossdraws", "artgerm greg rutkowski", "by ilya kuvshinov", "art by artgerm"]}, "biomechanical": {"similar": ["dystopian", "ominous", "expressive", "robotic", "new"], "unsimilar": ["baarle ilya kuvshinov", "ilya kuvshinov rossdraws", "artgerm greg rutkowski", "digital painting artstation", "painting artstation concept"]}, "and magali villeneuve": {"similar": ["magali villeneuve", "ruan jia and", "and intricate environment", "and greg rutkowski", "greg rutkowski and"], "unsimilar": ["baarle ilya kuvshinov", "artgerm greg rutkowski", "ilya kuvshinov rossdraws", "digital painting artstation", "smooth sharp focus"]}, "apocalyptic": {"similar": ["dystopian", "ominous", "cinematic", "atmospheric", "expressive"], "unsimilar": ["baarle ilya kuvshinov", "ilya kuvshinov rossdraws", "artgerm greg rutkowski", "by ilya kuvshinov", "art by artgerm"]}, "powerful": {"similar": ["dystopian", "ominous", "apocalyptic", "strong", "mysterious"], "unsimilar": ["baarle ilya kuvshinov", "ilya kuvshinov rossdraws", "artgerm greg rutkowski", "by ilya kuvshinov", "art by artgerm"]}, "great": {"similar": ["good", "dystopian", "ominous", "new", "many"], "unsimilar": ["baarle ilya kuvshinov", "ilya kuvshinov rossdraws", "artgerm greg rutkowski", "by ilya kuvshinov", "art by artgerm"]}, "ruan jia and": {"similar": ["ruan jia", "and intricate environment", "black and white", "and lois van", "and alphonse mucha"], "unsimilar": ["baarle ilya kuvshinov", "artgerm greg rutkowski", "ilya kuvshinov rossdraws", "digital painting artstation", "stanley artgerm lau"]}, "final": {"similar": ["ominous", "dystopian", "apocalyptic", "cinematic", "massive"], "unsimilar": ["baarle ilya kuvshinov", "ilya kuvshinov rossdraws", "artgerm greg rutkowski", "by ilya kuvshinov", "art by artgerm"]}, "industrial": {"similar": ["dystopian", "ominous", "apocalyptic", "atmospheric", "mystical"], "unsimilar": ["baarle ilya kuvshinov", "ilya kuvshinov rossdraws", "artgerm greg rutkowski", "by ilya kuvshinov", "art by artgerm"]}, "by gaston bussiere": {"similar": ["gaston bussiere", "art by greg", "illustration art by", "focus art by", "digital art by"], "unsimilar": ["baarle ilya kuvshinov", "ilya kuvshinov rossdraws", "artgerm greg rutkowski", "ilya kuvshinov", "matte sharp focus"]}, "hot": {"similar": ["dystopian", "ominous", "new", "good", "high"], "unsimilar": ["baarle ilya kuvshinov", "ilya kuvshinov rossdraws", "artgerm greg rutkowski", "by ilya kuvshinov", "art by artgerm"]}, "national": {"similar": ["dystopian", "ominous", "majestic", "natural", "mystical"], "unsimilar": ["baarle ilya kuvshinov", "ilya kuvshinov rossdraws", "artgerm greg rutkowski", "by ilya kuvshinov", "art by artgerm"]}, "ultradetailed": {"similar": ["detailed", "ultra detailed", "extremely detailed", "ultrarealistic", "hyper detailed"], "unsimilar": ["baarle ilya kuvshinov", "ilya kuvshinov rossdraws", "artgerm greg rutkowski", "by ilya kuvshinov", "art by artgerm"]}, "digital art by": {"similar": ["digital art", "digital art trending", "illustration art by", "art by greg", "focus art by"], "unsimilar": ["baarle ilya kuvshinov", "ilya kuvshinov rossdraws", "artgerm greg rutkowski", "donato giancola", "ilya kuvshinov"]}, "on artstation concept": {"similar": ["artstation concept", "painting artstation concept", "trending on artstation", "on art station", "painting artstation"], "unsimilar": ["baarle ilya kuvshinov", "ilya kuvshinov rossdraws", "intricate elegant highly", "tom bagshaw", "smooth sharp focus"]}, "expressive": {"similar": ["dystopian", "ominous", "apocalyptic", "dramatic", "atmospheric"], "unsimilar": ["baarle ilya kuvshinov", "ilya kuvshinov rossdraws", "artgerm greg rutkowski", "by ilya kuvshinov", "art by artgerm"]}, "unreal engine octane": {"similar": ["unreal engine", "render unreal engine", "octane render unreal", "render unreal", "octane render"], "unsimilar": ["baarle ilya kuvshinov", "artgerm greg rutkowski", "ilya kuvshinov rossdraws", "art by artgerm", "by stanley artgerm"]}, "on art station": {"similar": ["art station", "art trending on", "trending on art", "trending on artstation", "on artstation concept"], "unsimilar": ["baarle ilya kuvshinov", "ilya kuvshinov rossdraws", "artgerm greg rutkowski", "makoto shinkai", "ilya kuvshinov"]}, "focus art by": {"similar": ["focus illustration art", "art sharp focus", "sharp focus art", "illustration art by", "art by greg"], "unsimilar": ["baarle ilya kuvshinov", "ilya kuvshinov rossdraws", "artgerm greg rutkowski", "anthropomorphic", "makoto shinkai"]}, "artgerm greg rutkowski": {"similar": ["artgerm and greg", "stanley artgerm", "and greg rutkowski", "greg rutkowski and", "greg rutkowski"], "unsimilar": ["fantasy intricate elegant", "baarle ilya kuvshinov", "intricate elegant highly", "ilya kuvshinov rossdraws", "smooth sharp focus"]}, "trending on art": {"similar": ["art trending on", "art trending", "painting trending on", "render trending on", "on art station"], "unsimilar": ["baarle ilya kuvshinov", "ilya kuvshinov rossdraws", "artgerm greg rutkowski", "by ilya kuvshinov", "ilya kuvshinov"]}, "good": {"similar": ["ominous", "great", "dystopian", "high", "new"], "unsimilar": ["baarle ilya kuvshinov", "ilya kuvshinov rossdraws", "artgerm greg rutkowski", "by ilya kuvshinov", "art by artgerm"]}, "robotic": {"similar": ["dystopian", "ominous", "futuristic", "apocalyptic", "expressive"], "unsimilar": ["baarle ilya kuvshinov", "ilya kuvshinov rossdraws", "artgerm greg rutkowski", "by ilya kuvshinov", "art by artgerm"]}, "by stanley artgerm": {"similar": ["stanley artgerm", "art by artgerm", "stanley artgerm lau", "artgerm and greg", "artgerm greg rutkowski"], "unsimilar": ["baarle ilya kuvshinov", "fantasy intricate elegant", "ilya kuvshinov rossdraws", "intricate elegant highly", "unreal engine octane"]}, "other": {"similar": ["ominous", "dystopian", "new", "many", "apocalyptic"], "unsimilar": ["baarle ilya kuvshinov", "ilya kuvshinov rossdraws", "artgerm greg rutkowski", "by ilya kuvshinov", "ilya kuvshinov"]}, "body portrait of": {"similar": ["body portrait", "full body portrait", "portrait of beautiful", "portrait painting of", "full body"], "unsimilar": ["baarle ilya kuvshinov", "ilya kuvshinov rossdraws", "artgerm greg rutkowski", "by ilya kuvshinov", "ilya kuvshinov"]}, "league of legends": {"similar": ["rule of thirds", "depth of field", "oil painting of", "portrait of beautiful", "film still of"], "unsimilar": ["baarle ilya kuvshinov", "ilya kuvshinov rossdraws", "artgerm greg rutkowski", "by ilya kuvshinov", "ilya kuvshinov"]}, "asian": {"similar": ["dystopian", "ominous", "apocalyptic", "chinese", "japanese"], "unsimilar": ["baarle ilya kuvshinov", "ilya kuvshinov rossdraws", "artgerm greg rutkowski", "by ilya kuvshinov", "art by artgerm"]}, "incredible": {"similar": ["ominous", "dystopian", "apocalyptic", "huge", "massive"], "unsimilar": ["baarle ilya kuvshinov", "ilya kuvshinov rossdraws", "artgerm greg rutkowski", "by ilya kuvshinov", "art by artgerm"]}, "military": {"similar": ["dystopian", "ominous", "apocalyptic", "victorian", "cinematic"], "unsimilar": ["baarle ilya kuvshinov", "ilya kuvshinov rossdraws", "artgerm greg rutkowski", "by ilya kuvshinov", "art by artgerm"]}, "majestic": {"similar": ["ominous", "dystopian", "apocalyptic", "expressive", "mystical"], "unsimilar": ["baarle ilya kuvshinov", "ilya kuvshinov rossdraws", "artgerm greg rutkowski", "by ilya kuvshinov", "art by artgerm"]}, "visible": {"similar": ["ominous", "dystopian", "expressive", "visual", "mystical"], "unsimilar": ["baarle ilya kuvshinov", "ilya kuvshinov rossdraws", "artgerm greg rutkowski", "by ilya kuvshinov", "art by artgerm"]}, "french": {"similar": ["dystopian", "ominous", "red", "new", "chinese"], "unsimilar": ["baarle ilya kuvshinov", "ilya kuvshinov rossdraws", "artgerm greg rutkowski", "by ilya kuvshinov", "art by artgerm"]}, "anamorphic": {"similar": ["ominous", "dystopian", "huge", "massive", "atmospheric"], "unsimilar": ["baarle ilya kuvshinov", "ilya kuvshinov rossdraws", "artgerm greg rutkowski", "digital painting artstation", "art by artgerm"]}, "asymmetrical": {"similar": ["symmetrical", "dystopian", "ominous", "expressive", "futuristic"], "unsimilar": ["baarle ilya kuvshinov", "ilya kuvshinov rossdraws", "by ilya kuvshinov", "artgerm greg rutkowski", "art by artgerm"]}, "ultrarealistic": {"similar": ["realistic", "ultra realistic", "ultradetailed", "hyper realistic", "photorealistic"], "unsimilar": ["baarle ilya kuvshinov", "ilya kuvshinov rossdraws", "artgerm greg rutkowski", "by ilya kuvshinov", "art by artgerm"]}, "default": ["detailed", "highly detailed", "hyper detailed", "extremely detailed", "cinematic", "realistic", "concept art", "sharp", "greg rutkowski", "sharp focus"]}